Workbook

Sheet Dashboard
A1: Credit Risk Scoring Dashboard
A2: Consumer Credit Underwriting & Portfolio Risk Project | 500 synthetic borrowers
A4: Portfolio Credit Snapshot
A5: Borrowers | B5: Exposure | C5: Observed Default | D5: Avg. PD | E5: Expected Loss | F5: EL % Exposure | G5: Avg. Score | H5: High-Risk Exposure
A6: ='Model Performance'!B5 | B6: ='Model Performance'!B6 | C6: ='Model Performance'!B7 | D6: ='Model Performance'!B8 | E6: ='Model Performance'!B9 | F6: ='Model Performance'!B10 | G6: ='Model Performance'!B12 | H6: ='Model Performance'!B13
A8: Risk Tier Distribution
A9: Tier | B9: Borrowers | C9: Exposure | D9: Default Rate
A10: ='Model Performance'!A17 | B10: ='Model Performance'!B17 | C10: ='Model Performance'!C17 | D10: ='Model Performance'!D17
A11: ='Model Performance'!A18 | B11: ='Model Performance'!B18 | C11: ='Model Performance'!C18 | D11: ='Model Performance'!D18
A12: ='Model Performance'!A19 | B12: ='Model Performance'!B19 | C12: ='Model Performance'!C19 | D12: ='Model Performance'!D19
A13: ='Model Performance'!A20 | B13: ='Model Performance'!B20 | C13: ='Model Performance'!C20 | D13: ='Model Performance'!D20
A14: ='Model Performance'!A21 | B14: ='Model Performance'!B21 | C14: ='Model Performance'!C21 | D14: ='Model Performance'!D21
A22: Underwriting Takeaways
A23: The model combines FICO, debt-to-income, utilization, delinquency history, employment stability, loan-to-income and term into transparent risk points. The score maps to an estimated probability of default, risk tier and underwriting decision, while the portfolio view aggregates expected loss and high-risk exposure. This demonstrates both borrower-level underwriting and portfolio credit monitoring.

Sheet Scorecard
A1: Credit Risk Scorecard
A2: Illustrative consumer-loan underwriting model | Transparent points score + PD + risk tier
A4: Scoring Framework
A5: Factor | B5: Low Risk | C5: Moderate Risk | D5: High Risk | E5: Points
A6: FICO Score | B6: >=740 | C6: 670–739 | D6: <670 | E6: 0 / 15 / 30
A7: Debt-to-Income | B7: <=25% | C7: 25–40% | D7: >40% | E7: 0 / 15 / 30
A8: Utilization | B8: <=30% | C8: 30–60% | D8: >60% | E8: 0 / 10 / 20
A9: Delinquencies | B9: 0 | C9: 1 | D9: 2+ | E9: 0 / 10 / 25
A10: Employment Years | B10: >=5 | C10: 2–5 | D10: <2 | E10: 0 / 5 / 10
A11: Loan / Income | B11: <=25% | C11: 25–50% | D11: >50% | E11: 0 / 10 / 20
A12: Term | B12: 36 mo. | C12: 48 mo. | D12: 60 mo. | E12: 0 / 3 / 6
A14: Risk Tier Thresholds
A15: Points | B15: Tier | C15: Indicative PD | D15: Underwriting View
A16: 0–19 | B16: A | C16: <3% | D16: Low risk
A17: 20–39 | B17: B | C17: 3–7% | D17: Acceptable
A18: 40–59 | B18: C | C18: 7–15% | D18: Conditional
A19: 60–79 | B19: D | C19: 15–30% | D19: Enhanced review
A20: 80+ | B20: E | C20: >30% | D20: Very high risk

Sheet Loan Data
A1: Synthetic Loan-Level Dataset & Scoring Output
A2: 500 synthetic borrowers; blue cells are generated inputs, not real customer data. All risk outputs are formula-driven.
A4: Borrower ID | B4: Income | C4: DTI | D4: FICO | E4: Utilization | F4: Delinq. | G4: Employment Yrs | H4: Loan Amount | I4: Term | J4: Observed Default | K4: Risk Points | L4: Credit Score | M4: Est. PD | N4: Risk Tier | O4: Decision | P4: Expected Loss | Q4: Loan / Income
A5: B0001 | B5: 105283 | C5: 0.37917872 | D5: 687 | E5: 0.71645052 | F5: 0 | G5: 1.3 | H5: 16981 | I5: 60 | J5: 0 | K5: =IF(D5>=740,0,IF(D5>=670,15,30))+IF(C5<=25%,0,IF(C5<=40%,15,30))+IF(E5<=30%,0,IF(E5<=60%,10,20))+IF(F5=0,0,IF(F5=1,10,25))+IF(G5>=5,0,IF(G5>=2,5,10))+IF(H5/B5<=25%,0,IF(H5/B5<=50%,10,20))+IF(I5=36,0,IF(I5=48,3,6)) | L5: =850-K5*3.5 | M5: =1/(1+EXP(-(-4.2+0.055*K5))) | N5: =IF(K5<20,"A",IF(K5<40,"B",IF(K5<60,"C",IF(K5<80,"D","E")))) | O5: =IF(OR(N5="D",N5="E"),"Enhanced Review",IF(N5="C","Conditional","Approve")) | P5: =H5*M5*45% | Q5: =H5/B5
A6: B0002 | B6: 236249 | C6: 0.49857359 | D6: 641 | E6: 0.27256543 | F6: 0 | G6: 14.2 | H6: 28110 | I6: 60 | J6: 0 | K6: =IF(D6>=740,0,IF(D6>=670,15,30))+IF(C6<=25%,0,IF(C6<=40%,15,30))+IF(E6<=30%,0,IF(E6<=60%,10,20))+IF(F6=0,0,IF(F6=1,10,25))+IF(G6>=5,0,IF(G6>=2,5,10))+IF(H6/B6<=25%,0,IF(H6/B6<=50%,10,20))+IF(I6=36,0,IF(I6=48,3,6)) | L6: =850-K6*3.5 | M6: =1/(1+EXP(-(-4.2+0.055*K6))) | N6: =IF(K6<20,"A",IF(K6<40,"B",IF(K6<60,"C",IF(K6<80,"D","E")))) | O6: =IF(OR(N6="D",N6="E"),"Enhanced Review",IF(N6="C","Conditional","Approve")) | P6: =H6*M6*45% | Q6: =H6/B6
A7: B0003 | B7: 277445 | C7: 0.37441434 | D7: 658 | E7: 0.17017269 | F7: 0 | G7: 11.1 | H7: 18616 | I7: 36 | J7: 0 | K7: =IF(D7>=740,0,IF(D7>=670,15,30))+IF(C7<=25%,0,IF(C7<=40%,15,30))+IF(E7<=30%,0,IF(E7<=60%,10,20))+IF(F7=0,0,IF(F7=1,10,25))+IF(G7>=5,0,IF(G7>=2,5,10))+IF(H7/B7<=25%,0,IF(H7/B7<=50%,10,20))+IF(I7=36,0,IF(I7=48,3,6)) | L7: =850-K7*3.5 | M7: =1/(1+EXP(-(-4.2+0.055*K7))) | N7: =IF(K7<20,"A",IF(K7<40,"B",IF(K7<60,"C",IF(K7<80,"D","E")))) | O7: =IF(OR(N7="D",N7="E"),"Enhanced Review",IF(N7="C","Conditional","Approve")) | P7: =H7*M7*45% | Q7: =H7/B7
A8: B0004 | B8: 89446 | C8: 0.18916429 | D8: 681 | E8: 0.54014666 | F8: 1 | G8: 22.8 | H8: 16999 | I8: 36 | J8: 0 | K8: =IF(D8>=740,0,IF(D8>=670,15,30))+IF(C8<=25%,0,IF(C8<=40%,15,30))+IF(E8<=30%,0,IF(E8<=60%,10,20))+IF(F8=0,0,IF(F8=1,10,25))+IF(G8>=5,0,IF(G8>=2,5,10))+IF(H8/B8<=25%,0,IF(H8/B8<=50%,10,20))+IF(I8=36,0,IF(I8=48,3,6)) | L8: =850-K8*3.5 | M8: =1/(1+EXP(-(-4.2+0.055*K8))) | N8: =IF(K8<20,"A",IF(K8<40,"B",IF(K8<60,"C",IF(K8<80,"D","E")))) | O8: =IF(OR(N8="D",N8="E"),"Enhanced Review",IF(N8="C","Conditional","Approve")) | P8: =H8*M8*45% | Q8: =H8/B8
A9: B0005 | B9: 35828 | C9: 0.34525991 | D9: 734 | E9: 0.44033442 | F9: 0 | G9: 3.8 | H9: 30195 | I9: 60 | J9: 0 | K9: =IF(D9>=740,0,IF(D9>=670,15,30))+IF(C9<=25%,0,IF(C9<=40%,15,30))+IF(E9<=30%,0,IF(E9<=60%,10,20))+IF(F9=0,0,IF(F9=1,10,25))+IF(G9>=5,0,IF(G9>=2,5,10))+IF(H9/B9<=25%,0,IF(H9/B9<=50%,10,20))+IF(I9=36,0,IF(I9=48,3,6)) | L9: =850-K9*3.5 | M9: =1/(1+EXP(-(-4.2+0.055*K9))) | N9: =IF(K9<20,"A",IF(K9<40,"B",IF(K9<60,"C",IF(K9<80,"D","E")))) | O9: =IF(OR(N9="D",N9="E"),"Enhanced Review",IF(N9="C","Conditional","Approve")) | P9: =H9*M9*45% | Q9: =H9/B9
A10: B0006 | B10: 76524 | C10: 0.20092745 | D10: 762 | E10: 0.2627741 | F10: 0 | G10: 11.9 | H10: 42741 | I10: 36 | J10: 0 | K10: =IF(D10>=740,0,IF(D10>=670,15,30))+IF(C10<=25%,0,IF(C10<=40%,15,30))+IF(E10<=30%,0,IF(E10<=60%,10,20))+IF(F10=0,0,IF(F10=1,10,25))+IF(G10>=5,0,IF(G10>=2,5,10))+IF(H10/B10<=25%,0,IF(H10/B10<=50%,10,20))+IF(I10=36,0,IF(I10=48,3,6)) | L10: =850-K10*3.5 | M10: =1/(1+EXP(-(-4.2+0.055*K10))) | N10: =IF(K10<20,"A",IF(K10<40,"B",IF(K10<60,"C",IF(K10<80,"D","E")))) | O10: =IF(OR(N10="D",N10="E"),"Enhanced Review",IF(N10="C","Conditional","Approve")) | P10: =H10*M10*45% | Q10: =H10/B10
A11: B0007 | B11: 97580 | C11: 0.4027013 | D11: 623 | E11: 0.10392827 | F11: 0 | G11: 14.5 | H11: 16583 | I11: 48 | J11: 0 | K11: =IF(D11>=740,0,IF(D11>=670,15,30))+IF(C11<=25%,0,IF(C11<=40%,15,30))+IF(E11<=30%,0,IF(E11<=60%,10,20))+IF(F11=0,0,IF(F11=1,10,25))+IF(G11>=5,0,IF(G11>=2,5,10))+IF(H11/B11<=25%,0,IF(H11/B11<=50%,10,20))+IF(I11=36,0,IF(I11=48,3,6)) | L11: =850-K11*3.5 | M11: =1/(1+EXP(-(-4.2+0.055*K11))) | N11: =IF(K11<20,"A",IF(K11<40,"B",IF(K11<60,"C",IF(K11<80,"D","E")))) | O11: =IF(OR(N11="D",N11="E"),"Enhanced Review",IF(N11="C","Conditional","Approve")) | P11: =H11*M11*45% | Q11: =H11/B11
A12: B0008 | B12: 35212 | C12: 0.21730264 | D12: 610 | E12: 0.50332314 | F12: 0 | G12: 2 | H12: 14029 | I12: 36 | J12: 1 | K12: =IF(D12>=740,0,IF(D12>=670,15,30))+IF(C12<=25%,0,IF(C12<=40%,15,30))+IF(E12<=30%,0,IF(E12<=60%,10,20))+IF(F12=0,0,IF(F12=1,10,25))+IF(G12>=5,0,IF(G12>=2,5,10))+IF(H12/B12<=25%,0,IF(H12/B12<=50%,10,20))+IF(I12=36,0,IF(I12=48,3,6)) | L12: =850-K12*3.5 | M12: =1/(1+EXP(-(-4.2+0.055*K12))) | N12: =IF(K12<20,"A",IF(K12<40,"B",IF(K12<60,"C",IF(K12<80,"D","E")))) | O12: =IF(OR(N12="D",N12="E"),"Enhanced Review",IF(N12="C","Conditional","Approve")) | P12: =H12*M12*45% | Q12: =H12/B12
A13: B0009 | B13: 53355 | C13: 0.18051601 | D13: 744 | E13: 0.69405842 | F13: 0 | G13: 2.2 | H13: 16147 | I13: 60 | J13: 0 | K13: =IF(D13>=740,0,IF(D13>=670,15,30))+IF(C13<=25%,0,IF(C13<=40%,15,30))+IF(E13<=30%,0,IF(E13<=60%,10,20))+IF(F13=0,0,IF(F13=1,10,25))+IF(G13>=5,0,IF(G13>=2,5,10))+IF(H13/B13<=25%,0,IF(H13/B13<=50%,10,20))+IF(I13=36,0,IF(I13=48,3,6)) | L13: =850-K13*3.5 | M13: =1/(1+EXP(-(-4.2+0.055*K13))) | N13: =IF(K13<20,"A",IF(K13<40,"B",IF(K13<60,"C",IF(K13<80,"D","E")))) | O13: =IF(OR(N13="D",N13="E"),"Enhanced Review",IF(N13="C","Conditional","Approve")) | P13: =H13*M13*45% | Q13: =H13/B13
A14: B0010 | B14: 134746 | C14: 0.10339965 | D14: 764 | E14: 0.15747811 | F14: 0 | G14: 4.3 | H14: 4978 | I14: 36 | J14: 0 | K14: =IF(D14>=740,0,IF(D14>=670,15,30))+IF(C14<=25%,0,IF(C14<=40%,15,30))+IF(E14<=30%,0,IF(E14<=60%,10,20))+IF(F14=0,0,IF(F14=1,10,25))+IF(G14>=5,0,IF(G14>=2,5,10))+IF(H14/B14<=25%,0,IF(H14/B14<=50%,10,20))+IF(I14=36,0,IF(I14=48,3,6)) | L14: =850-K14*3.5 | M14: =1/(1+EXP(-(-4.2+0.055*K14))) | N14: =IF(K14<20,"A",IF(K14<40,"B",IF(K14<60,"C",IF(K14<80,"D","E")))) | O14: =IF(OR(N14="D",N14="E"),"Enhanced Review",IF(N14="C","Conditional","Approve")) | P14: =H14*M14*45% | Q14: =H14/B14
A15: B0011 | B15: 181091 | C15: 0.31583595 | D15: 686 | E15: 0.39191647 | F15: 0 | G15: 3 | H15: 13373 | I15: 48 | J15: 0 | K15: =IF(D15>=740,0,IF(D15>=670,15,30))+IF(C15<=25%,0,IF(C15<=40%,15,30))+IF(E15<=30%,0,IF(E15<=60%,10,20))+IF(F15=0,0,IF(F15=1,10,25))+IF(G15>=5,0,IF(G15>=2,5,10))+IF(H15/B15<=25%,0,IF(H15/B15<=50%,10,20))+IF(I15=36,0,IF(I15=48,3,6)) | L15: =850-K15*3.5 | M15: =1/(1+EXP(-(-4.2+0.055*K15))) | N15: =IF(K15<20,"A",IF(K15<40,"B",IF(K15<60,"C",IF(K15<80,"D","E")))) | O15: =IF(OR(N15="D",N15="E"),"Enhanced Review",IF(N15="C","Conditional","Approve")) | P15: =H15*M15*45% | Q15: =H15/B15
A16: B0012 | B16: 33856 | C16: 0.46350344 | D16: 686 | E16: 0.90999124 | F16: 1 | G16: 8.6 | H16: 15722 | I16: 60 | J16: 0 | K16: =IF(D16>=740,0,IF(D16>=670,15,30))+IF(C16<=25%,0,IF(C16<=40%,15,30))+IF(E16<=30%,0,IF(E16<=60%,10,20))+IF(F16=0,0,IF(F16=1,10,25))+IF(G16>=5,0,IF(G16>=2,5,10))+IF(H16/B16<=25%,0,IF(H16/B16<=50%,10,20))+IF(I16=36,0,IF(I16=48,3,6)) | L16: =850-K16*3.5 | M16: =1/(1+EXP(-(-4.2+0.055*K16))) | N16: =IF(K16<20,"A",IF(K16<40,"B",IF(K16<60,"C",IF(K16<80,"D","E")))) | O16: =IF(OR(N16="D",N16="E"),"Enhanced Review",IF(N16="C","Conditional","Approve")) | P16: =H16*M16*45% | Q16: =H16/B16
... A504: B0500 | B504: 48930 | C504: 0.17997356 | D504: 783 | E504: 0.62591267 | F504: 2 | G504: 4.8 | H504: 51307 | I504: 60 | J504: 0 | K504: =IF(D504>=740,0,IF(D504>=670,15,30))+IF(C504<=25%,0,IF(C504<=40%,15,30))+IF(E504<=30%,0,IF(E504<=60%,10,20))+IF(F504=0,0,IF(F504=1,10,25))+IF(G504>=5,0,IF(G504>=2,5,10))+IF(H504/B504<=25%,0,IF(H504/B504<=50%,10,20))+IF(I504=36,0,IF(I504=48,3,6)) | L504: =850-K504*3.5 | M504: =1/(1+EXP(-(-4.2+0.055*K504))) | N504: =IF(K504<20,"A",IF(K504<40,"B",IF(K504<60,"C",IF(K504<80,"D","E")))) | O504: =IF(OR(N504="D",N504="E"),"Enhanced Review",IF(N504="C","Conditional","Approve")) | P504: =H504*M504*45% | Q504: =H504/B504

Sheet Model Performance
A1: Model Performance & Credit Portfolio Analytics
A3: Portfolio Metrics
A4: Metric | B4: Result | C4: Context | D4: Interpretation
A5: Borrowers | B5: =COUNTA('Loan Data'!A5:A504) | C5: Synthetic dataset | D5: Sample size
A6: Total Exposure | B6: =SUM('Loan Data'!H5:H504) | C6: Principal balance | D6: Gross exposure
A7: Observed Default Rate | B7: =AVERAGE('Loan Data'!J5:J504) | C7: Synthetic outcome | D7: Realized scenario bad rate
A8: Average Estimated PD | B8: =AVERAGE('Loan Data'!M5:M504) | C8: Model output | D8: Forward-looking risk estimate
A9: Expected Loss | B9: =SUM('Loan Data'!P5:P504) | C9: PD × EAD × 45% LGD | D9: Expected dollar loss
A10: Expected Loss % Exposure | B10: =B9/B6 | C10: Portfolio credit cost | D10: Loss intensity
A11: Average Risk Points | B11: =AVERAGE('Loan Data'!K5:K504) | C11: 0 = best | D11: Higher = riskier
A12: Average Credit Score | B12: =AVERAGE('Loan Data'!L5:L504) | C12: 850 = best | D12: Presentation score
A13: High-Risk Exposure (D/E) | B13: =SUMIF('Loan Data'!N5:N504,"D",'Loan Data'!H5:H504)+SUMIF('Loan Data'!N5:N504,"E",'Loan Data'!H5:H504) | C13: D/E exposure | D13: Weakest tiers
A15: Risk Tier Distribution
A16: Tier | B16: Borrowers | C16: Exposure | D16: Default Rate
A17: A | B17: =COUNTIF('Loan Data'!N5:N504,A17) | C17: =SUMIF('Loan Data'!N5:N504,A17,'Loan Data'!H5:H504) | D17: =IFERROR(SUMIFS('Loan Data'!J5:J504,'Loan Data'!N5:N504,A17)/B17,0)
A18: B | B18: =COUNTIF('Loan Data'!N5:N504,A18) | C18: =SUMIF('Loan Data'!N5:N504,A18,'Loan Data'!H5:H504) | D18: =IFERROR(SUMIFS('Loan Data'!J5:J504,'Loan Data'!N5:N504,A18)/B18,0)
A19: C | B19: =COUNTIF('Loan Data'!N5:N504,A19) | C19: =SUMIF('Loan Data'!N5:N504,A19,'Loan Data'!H5:H504) | D19: =IFERROR(SUMIFS('Loan Data'!J5:J504,'Loan Data'!N5:N504,A19)/B19,0)
A20: D | B20: =COUNTIF('Loan Data'!N5:N504,A20) | C20: =SUMIF('Loan Data'!N5:N504,A20,'Loan Data'!H5:H504) | D20: =IFERROR(SUMIFS('Loan Data'!J5:J504,'Loan Data'!N5:N504,A20)/B20,0)
A21: E | B21: =COUNTIF('Loan Data'!N5:N504,A21) | C21: =SUMIF('Loan Data'!N5:N504,A21,'Loan Data'!H5:H504) | D21: =IFERROR(SUMIFS('Loan Data'!J5:J504,'Loan Data'!N5:N504,A21)/B21,0)
A23: Simple Validation
A24: Measure | B24: Result | C24: Purpose | D24: Interpretation
A25: Default Rate: Score <650 | B25: =IFERROR(AVERAGEIF('Loan Data'!L5:L504,"<650",'Loan Data'!J5:J504),0) | C25: High-risk cohort | D25: Should be higher
A26: Default Rate: Score >=650 | B26: =IFERROR(AVERAGEIF('Loan Data'!L5:L504,">=650",'Loan Data'!J5:J504),0) | C26: Lower-risk cohort | D26: Should be lower
A27: Risk Separation | B27: =B25-B26 | C27: Score differentiation | D27: Positive is desirable

Sheet Methodology
A1: Methodology, Assumptions & Limitations
A3: Item | B3: Method | C3: Purpose | D3: Limitation
A4: Dataset | B4: 500 synthetic borrowers | C4: Demonstrate scoring and analytics | D4: No real customer/PII data
A5: Scorecard | B5: Transparent additive points | C5: Auditable underwriting logic | D5: Not a production model
A6: Estimated PD | B6: Logistic transform of risk points | C6: Probability of default | D6: Illustrative calibration
A7: Expected Loss | B7: PD × EAD × 45% LGD | C7: Quantify credit loss | D7: LGD is illustrative
A8: Validation | B8: Default-rate separation by score | C8: Basic discriminatory check | D8: Not independent validation
A9: Fair lending | B9: No protected attributes included | C9: Reduce direct sensitive-variable use | D9: Production requires proxy/disparate-impact testing
A11: Important Note
A12: For educational and recruiting use only. This workbook must not be used to approve or deny real credit applications. Production models require representative historical performance data, independent validation, model-risk governance, fair-lending testing, adverse-action reason codes, drift monitoring, and compliance review.
